starguard.py
starguard-0.1.0.dist-info/licenses/LICENSE
starguard-0.1.0.dist-info/METADATA
starguard-0.1.0.dist-info/WHEEL
starguard-0.1.0.dist-info/entry_points.txt
starguard-0.1.0.dist-info/top_level.txt
starguard-0.1.0.dist-info/RECORD
