Metadata-Version: 2.4
Name: starguard
Version: 0.1.0
Summary: GitHub Repository Analysis Tool with Advanced Fake Star Detection
Author-email: Mohamed Ahmed Elbeskeri <mohamed.ahmed.4894@gmail.com>
License: Apache-2.0
Project-URL: Homepage, https://github.com/yourusername/starguard
Project-URL: Bug Tracker, https://github.com/yourusername/starguard/issues
Keywords: github,security,analysis,fake-stars,repository
Classifier: Programming Language :: Python :: 3
Classifier: License :: OSI Approved :: Apache Software License
Classifier: Operating System :: OS Independent
Classifier: Development Status :: 4 - Beta
Classifier: Intended Audience :: Developers
Classifier: Topic :: Software Development :: Quality Assurance
Classifier: Topic :: Software Development :: Testing
Requires-Python: >=3.8
License-File: LICENSE
Requires-Dist: requests
Requires-Dist: numpy
Requires-Dist: pandas
Requires-Dist: scikit-learn
Requires-Dist: matplotlib
Requires-Dist: networkx
Requires-Dist: python-dateutil
Requires-Dist: tqdm
Dynamic: license-file
